llama_index/tools/yahoo_finance/__init__.py
llama_index/tools/yahoo_finance/base.py
llama_index_tools_yahoo_finance-0.4.1.dist-info/METADATA
llama_index_tools_yahoo_finance-0.4.1.dist-info/WHEEL
llama_index_tools_yahoo_finance-0.4.1.dist-info/licenses/LICENSE
llama_index_tools_yahoo_finance-0.4.1.dist-info/RECORD
