Metadata-Version: 2.4
Name: llama-index-tools-yahoo-finance
Version: 0.4.1
Summary: llama-index tools yahoo_finance integration
Author-email: Your Name <you@example.com>
License-Expression: MIT
License-File: LICENSE
Requires-Python: <4.0,>=3.9
Requires-Dist: llama-index-core<0.15,>=0.13.0
Requires-Dist: pandas
Requires-Dist: yfinance<0.3,>=0.2.36
